<?xml version="1.0" encoding="UTF-8"?>
<ValueSet
    xmlns="http://hl7.org/fhir">
    <id value="ValueSet-JP-REZEPT-RezeptSpecialInstruction"/>
    <meta>
        <versionId value="5"/>
        <lastUpdated value="2021-05-07T03:02:22.239+00:00"/>
        <source value="#haRNIKjp2mGXHILP"/>
    </meta>
    <url value="https://igs.healthdataworks.net/jp-rezept-medication/ValueSet-ValueSet-JP-REZEPT-RezeptSpecialInstruction.html"/>
    <name value="RezeptSpecialInstruction"/>
    <title value="レセプト特記事項コード"/>
    <status value="draft"/>
    <description value="このバリューセットには、レセプト電算処理システムで定義されているレセプト特記事項が含まれます。"/>
    <compose>
        <include>
            <system value="https://igs.healthdataworks.net/jp-rezept-medication/CodeSystem-CodeSystem-JP-REZEPT-RezeptSpecialInstructions.html"/>
        </include>
    </compose>
</ValueSet>